odoo/addons/stock_picking_group_by_partner_by_carrier_by_date/README.rst
odoo/addons/stock_picking_group_by_partner_by_carrier_by_date/__init__.py
odoo/addons/stock_picking_group_by_partner_by_carrier_by_date/__manifest__.py
odoo/addons/stock_picking_group_by_partner_by_carrier_by_date/i18n/stock_picking_group_by_partner_by_carrier_by_date.pot
odoo/addons/stock_picking_group_by_partner_by_carrier_by_date/models/__init__.py
odoo/addons/stock_picking_group_by_partner_by_carrier_by_date/models/stock_move.py
odoo/addons/stock_picking_group_by_partner_by_carrier_by_date/models/stock_picking_type.py
odoo/addons/stock_picking_group_by_partner_by_carrier_by_date/readme/CONTRIBUTORS.rst
odoo/addons/stock_picking_group_by_partner_by_carrier_by_date/readme/DESCRIPTION.rst
odoo/addons/stock_picking_group_by_partner_by_carrier_by_date/readme/USAGE.rst
odoo/addons/stock_picking_group_by_partner_by_carrier_by_date/static/description/icon.png
odoo/addons/stock_picking_group_by_partner_by_carrier_by_date/static/description/index.html
odoo/addons/stock_picking_group_by_partner_by_carrier_by_date/tests/__init__.py
odoo/addons/stock_picking_group_by_partner_by_carrier_by_date/tests/test_grouping_by_date.py
odoo/addons/stock_picking_group_by_partner_by_carrier_by_date/views/stock_picking_type.xml
odoo13_addon_stock_picking_group_by_partner_by_carrier_by_date-13.0.1.1.1.dist-info/METADATA
odoo13_addon_stock_picking_group_by_partner_by_carrier_by_date-13.0.1.1.1.dist-info/WHEEL
odoo13_addon_stock_picking_group_by_partner_by_carrier_by_date-13.0.1.1.1.dist-info/top_level.txt
odoo13_addon_stock_picking_group_by_partner_by_carrier_by_date-13.0.1.1.1.dist-info/RECORD
